{
  "tkidx_ueno_booking_top3_all": {
    "provider": "booking_travelpayouts",
    "area_id": "ueno",
    "locale": "all",
    "placement": "top3",
    "destination_url": "",
    "affiliate_url": "",
    "sub_id": "fs_tkidx_top3_ueno_all",
    "enabled": true,
    "priority": 10,
    "last_checked_at": "",
    "notes": "",
    "destination_ref": "booking_ueno"
  },
  "tkidx_ueno_booking_detail_all": {
    "provider": "booking_travelpayouts",
    "area_id": "ueno",
    "locale": "all",
    "placement": "detail",
    "destination_url": "",
    "affiliate_url": "",
    "sub_id": "fs_tkidx_detail_ueno_all",
    "enabled": true,
    "priority": 10,
    "last_checked_at": "",
    "notes": "",
    "destination_ref": "booking_ueno"
  },
  "tkidx_asakusa_booking_top3_all": {
    "provider": "booking_travelpayouts",
    "area_id": "asakusa",
    "locale": "all",
    "placement": "top3",
    "destination_url": "",
    "affiliate_url": "",
    "sub_id": "fs_tkidx_top3_asakusa_all",
    "enabled": true,
    "priority": 10,
    "last_checked_at": "",
    "notes": "",
    "destination_ref": "booking_asakusa"
  },
  "tkidx_asakusa_booking_detail_all": {
    "provider": "booking_travelpayouts",
    "area_id": "asakusa",
    "locale": "all",
    "placement": "detail",
    "destination_url": "",
    "affiliate_url": "",
    "sub_id": "fs_tkidx_detail_asakusa_all",
    "enabled": true,
    "priority": 10,
    "last_checked_at": "",
    "notes": "",
    "destination_ref": "booking_asakusa"
  },
  "tkidx_oshiage_booking_top3_all": {
    "provider": "booking_travelpayouts",
    "area_id": "oshiage",
    "locale": "all",
    "placement": "top3",
    "destination_url": "",
    "affiliate_url": "",
    "sub_id": "fs_tkidx_top3_oshiage_all",
    "enabled": true,
    "priority": 10,
    "last_checked_at": "",
    "notes": "",
    "destination_ref": "booking_oshiage"
  },
  "tkidx_oshiage_booking_detail_all": {
    "provider": "booking_travelpayouts",
    "area_id": "oshiage",
    "locale": "all",
    "placement": "detail",
    "destination_url": "",
    "affiliate_url": "",
    "sub_id": "fs_tkidx_detail_oshiage_all",
    "enabled": true,
    "priority": 10,
    "last_checked_at": "",
    "notes": "",
    "destination_ref": "booking_oshiage"
  },
  "tkidx_tokyo_station_booking_top3_all": {
    "provider": "booking_travelpayouts",
    "area_id": "tokyo-station",
    "locale": "all",
    "placement": "top3",
    "destination_url": "",
    "affiliate_url": "",
    "sub_id": "fs_tkidx_top3_tokyo-station_all",
    "enabled": true,
    "priority": 10,
    "last_checked_at": "",
    "notes": "",
    "destination_ref": "booking_tokyo-station"
  },
  "tkidx_tokyo_station_booking_detail_all": {
    "provider": "booking_travelpayouts",
    "area_id": "tokyo-station",
    "locale": "all",
    "placement": "detail",
    "destination_url": "",
    "affiliate_url": "",
    "sub_id": "fs_tkidx_detail_tokyo-station_all",
    "enabled": true,
    "priority": 10,
    "last_checked_at": "",
    "notes": "",
    "destination_ref": "booking_tokyo-station"
  },
  "tkidx_nihombashi_booking_top3_all": {
    "provider": "booking_travelpayouts",
    "area_id": "nihombashi",
    "locale": "all",
    "placement": "top3",
    "destination_url": "",
    "affiliate_url": "",
    "sub_id": "fs_tkidx_top3_nihombashi_all",
    "enabled": true,
    "priority": 10,
    "last_checked_at": "",
    "notes": "",
    "destination_ref": "booking_nihombashi"
  },
  "tkidx_nihombashi_booking_detail_all": {
    "provider": "booking_travelpayouts",
    "area_id": "nihombashi",
    "locale": "all",
    "placement": "detail",
    "destination_url": "",
    "affiliate_url": "",
    "sub_id": "fs_tkidx_detail_nihombashi_all",
    "enabled": true,
    "priority": 10,
    "last_checked_at": "",
    "notes": "",
    "destination_ref": "booking_nihombashi"
  },
  "tkidx_ginza_yurakucho_booking_top3_all": {
    "provider": "booking_travelpayouts",
    "area_id": "ginza-yurakucho",
    "locale": "all",
    "placement": "top3",
    "destination_url": "",
    "affiliate_url": "",
    "sub_id": "fs_tkidx_top3_ginza-yurakucho_all",
    "enabled": true,
    "priority": 10,
    "last_checked_at": "",
    "notes": "",
    "destination_ref": "booking_ginza-yurakucho"
  },
  "tkidx_ginza_yurakucho_booking_detail_all": {
    "provider": "booking_travelpayouts",
    "area_id": "ginza-yurakucho",
    "locale": "all",
    "placement": "detail",
    "destination_url": "",
    "affiliate_url": "",
    "sub_id": "fs_tkidx_detail_ginza-yurakucho_all",
    "enabled": true,
    "priority": 10,
    "last_checked_at": "",
    "notes": "",
    "destination_ref": "booking_ginza-yurakucho"
  },
  "tkidx_shinjuku_booking_top3_all": {
    "provider": "booking_travelpayouts",
    "area_id": "shinjuku",
    "locale": "all",
    "placement": "top3",
    "destination_url": "",
    "affiliate_url": "",
    "sub_id": "fs_tkidx_top3_shinjuku_all",
    "enabled": true,
    "priority": 10,
    "last_checked_at": "",
    "notes": "",
    "destination_ref": "booking_shinjuku"
  },
  "tkidx_shinjuku_booking_detail_all": {
    "provider": "booking_travelpayouts",
    "area_id": "shinjuku",
    "locale": "all",
    "placement": "detail",
    "destination_url": "",
    "affiliate_url": "",
    "sub_id": "fs_tkidx_detail_shinjuku_all",
    "enabled": true,
    "priority": 10,
    "last_checked_at": "",
    "notes": "",
    "destination_ref": "booking_shinjuku"
  },
  "tkidx_shibuya_booking_top3_all": {
    "provider": "booking_travelpayouts",
    "area_id": "shibuya",
    "locale": "all",
    "placement": "top3",
    "destination_url": "",
    "affiliate_url": "",
    "sub_id": "fs_tkidx_top3_shibuya_all",
    "enabled": true,
    "priority": 10,
    "last_checked_at": "",
    "notes": "",
    "destination_ref": "booking_shibuya"
  },
  "tkidx_shibuya_booking_detail_all": {
    "provider": "booking_travelpayouts",
    "area_id": "shibuya",
    "locale": "all",
    "placement": "detail",
    "destination_url": "",
    "affiliate_url": "",
    "sub_id": "fs_tkidx_detail_shibuya_all",
    "enabled": true,
    "priority": 10,
    "last_checked_at": "",
    "notes": "",
    "destination_ref": "booking_shibuya"
  },
  "tkidx_shinagawa_booking_top3_all": {
    "provider": "booking_travelpayouts",
    "area_id": "shinagawa",
    "locale": "all",
    "placement": "top3",
    "destination_url": "",
    "affiliate_url": "",
    "sub_id": "fs_tkidx_top3_shinagawa_all",
    "enabled": true,
    "priority": 10,
    "last_checked_at": "",
    "notes": "",
    "destination_ref": "booking_shinagawa"
  },
  "tkidx_shinagawa_booking_detail_all": {
    "provider": "booking_travelpayouts",
    "area_id": "shinagawa",
    "locale": "all",
    "placement": "detail",
    "destination_url": "",
    "affiliate_url": "",
    "sub_id": "fs_tkidx_detail_shinagawa_all",
    "enabled": true,
    "priority": 10,
    "last_checked_at": "",
    "notes": "",
    "destination_ref": "booking_shinagawa"
  },
  "tkidx_hamamatsucho_daimon_booking_top3_all": {
    "provider": "booking_travelpayouts",
    "area_id": "hamamatsucho-daimon",
    "locale": "all",
    "placement": "top3",
    "destination_url": "",
    "affiliate_url": "",
    "sub_id": "fs_tkidx_top3_hamamatsucho-daimon_all",
    "enabled": true,
    "priority": 10,
    "last_checked_at": "",
    "notes": "",
    "destination_ref": "booking_hamamatsucho-daimon"
  },
  "tkidx_hamamatsucho_daimon_booking_detail_all": {
    "provider": "booking_travelpayouts",
    "area_id": "hamamatsucho-daimon",
    "locale": "all",
    "placement": "detail",
    "destination_url": "",
    "affiliate_url": "",
    "sub_id": "fs_tkidx_detail_hamamatsucho-daimon_all",
    "enabled": true,
    "priority": 10,
    "last_checked_at": "",
    "notes": "",
    "destination_ref": "booking_hamamatsucho-daimon"
  },
  "tkidx_hatchobori_booking_top3_all": {
    "provider": "booking_travelpayouts",
    "area_id": "hatchobori",
    "locale": "all",
    "placement": "top3",
    "destination_url": "",
    "affiliate_url": "",
    "sub_id": "fs_tkidx_top3_hatchobori_all",
    "enabled": true,
    "priority": 10,
    "last_checked_at": "",
    "notes": "",
    "destination_ref": "booking_hatchobori"
  },
  "tkidx_hatchobori_booking_detail_all": {
    "provider": "booking_travelpayouts",
    "area_id": "hatchobori",
    "locale": "all",
    "placement": "detail",
    "destination_url": "",
    "affiliate_url": "",
    "sub_id": "fs_tkidx_detail_hatchobori_all",
    "enabled": true,
    "priority": 10,
    "last_checked_at": "",
    "notes": "",
    "destination_ref": "booking_hatchobori"
  },
  "tkidx_kayabacho_booking_top3_all": {
    "provider": "booking_travelpayouts",
    "area_id": "kayabacho",
    "locale": "all",
    "placement": "top3",
    "destination_url": "",
    "affiliate_url": "",
    "sub_id": "fs_tkidx_top3_kayabacho_all",
    "enabled": true,
    "priority": 10,
    "last_checked_at": "",
    "notes": "",
    "destination_ref": "booking_kayabacho"
  },
  "tkidx_kayabacho_booking_detail_all": {
    "provider": "booking_travelpayouts",
    "area_id": "kayabacho",
    "locale": "all",
    "placement": "detail",
    "destination_url": "",
    "affiliate_url": "",
    "sub_id": "fs_tkidx_detail_kayabacho_all",
    "enabled": true,
    "priority": 10,
    "last_checked_at": "",
    "notes": "",
    "destination_ref": "booking_kayabacho"
  },
  "tkidx_akihabara_booking_top3_all": {
    "provider": "booking_travelpayouts",
    "area_id": "akihabara",
    "locale": "all",
    "placement": "top3",
    "destination_url": "",
    "affiliate_url": "",
    "sub_id": "fs_tkidx_top3_akihabara_all",
    "enabled": true,
    "priority": 10,
    "last_checked_at": "",
    "notes": "",
    "destination_ref": "booking_akihabara"
  },
  "tkidx_akihabara_booking_detail_all": {
    "provider": "booking_travelpayouts",
    "area_id": "akihabara",
    "locale": "all",
    "placement": "detail",
    "destination_url": "",
    "affiliate_url": "",
    "sub_id": "fs_tkidx_detail_akihabara_all",
    "enabled": true,
    "priority": 10,
    "last_checked_at": "",
    "notes": "",
    "destination_ref": "booking_akihabara"
  },
  "tkidx_kanda_booking_top3_all": {
    "provider": "booking_travelpayouts",
    "area_id": "kanda",
    "locale": "all",
    "placement": "top3",
    "destination_url": "",
    "affiliate_url": "",
    "sub_id": "fs_tkidx_top3_kanda_all",
    "enabled": true,
    "priority": 10,
    "last_checked_at": "",
    "notes": "",
    "destination_ref": "booking_kanda"
  },
  "tkidx_kanda_booking_detail_all": {
    "provider": "booking_travelpayouts",
    "area_id": "kanda",
    "locale": "all",
    "placement": "detail",
    "destination_url": "",
    "affiliate_url": "",
    "sub_id": "fs_tkidx_detail_kanda_all",
    "enabled": true,
    "priority": 10,
    "last_checked_at": "",
    "notes": "",
    "destination_ref": "booking_kanda"
  },
  "tkidx_kuramae_booking_top3_all": {
    "provider": "booking_travelpayouts",
    "area_id": "kuramae",
    "locale": "all",
    "placement": "top3",
    "destination_url": "",
    "affiliate_url": "",
    "sub_id": "fs_tkidx_top3_kuramae_all",
    "enabled": true,
    "priority": 10,
    "last_checked_at": "",
    "notes": "",
    "destination_ref": "booking_kuramae"
  },
  "tkidx_kuramae_booking_detail_all": {
    "provider": "booking_travelpayouts",
    "area_id": "kuramae",
    "locale": "all",
    "placement": "detail",
    "destination_url": "",
    "affiliate_url": "",
    "sub_id": "fs_tkidx_detail_kuramae_all",
    "enabled": true,
    "priority": 10,
    "last_checked_at": "",
    "notes": "",
    "destination_ref": "booking_kuramae"
  },
  "tkidx_kiyosumi_shirakawa_booking_top3_all": {
    "provider": "booking_travelpayouts",
    "area_id": "kiyosumi-shirakawa",
    "locale": "all",
    "placement": "top3",
    "destination_url": "",
    "affiliate_url": "",
    "sub_id": "fs_tkidx_top3_kiyosumi-shirakawa_all",
    "enabled": true,
    "priority": 10,
    "last_checked_at": "",
    "notes": "",
    "destination_ref": "booking_kiyosumi-shirakawa"
  },
  "tkidx_kiyosumi_shirakawa_booking_detail_all": {
    "provider": "booking_travelpayouts",
    "area_id": "kiyosumi-shirakawa",
    "locale": "all",
    "placement": "detail",
    "destination_url": "",
    "affiliate_url": "",
    "sub_id": "fs_tkidx_detail_kiyosumi-shirakawa_all",
    "enabled": true,
    "priority": 10,
    "last_checked_at": "",
    "notes": "",
    "destination_ref": "booking_kiyosumi-shirakawa"
  },
  "tkidx_ikebukuro_booking_top3_all": {
    "provider": "booking_travelpayouts",
    "area_id": "ikebukuro",
    "locale": "all",
    "placement": "top3",
    "destination_url": "",
    "affiliate_url": "",
    "sub_id": "fs_tkidx_top3_ikebukuro_all",
    "enabled": true,
    "priority": 10,
    "last_checked_at": "",
    "notes": "",
    "destination_ref": "booking_ikebukuro"
  },
  "tkidx_ikebukuro_booking_detail_all": {
    "provider": "booking_travelpayouts",
    "area_id": "ikebukuro",
    "locale": "all",
    "placement": "detail",
    "destination_url": "",
    "affiliate_url": "",
    "sub_id": "fs_tkidx_detail_ikebukuro_all",
    "enabled": true,
    "priority": 10,
    "last_checked_at": "",
    "notes": "",
    "destination_ref": "booking_ikebukuro"
  },
  "tkidx_ryogoku_booking_top3_all": {
    "provider": "booking_travelpayouts",
    "area_id": "ryogoku",
    "locale": "all",
    "placement": "top3",
    "destination_ref": "booking_ryogoku",
    "destination_url": "",
    "affiliate_url": "",
    "sub_id": "fs_tkidx_top3_ryogoku_all",
    "enabled": true,
    "priority": 10,
    "last_checked_at": "",
    "notes": ""
  },
  "tkidx_ryogoku_booking_detail_all": {
    "provider": "booking_travelpayouts",
    "area_id": "ryogoku",
    "locale": "all",
    "placement": "detail",
    "destination_ref": "booking_ryogoku",
    "destination_url": "",
    "affiliate_url": "",
    "sub_id": "fs_tkidx_detail_ryogoku_all",
    "enabled": true,
    "priority": 10,
    "last_checked_at": "",
    "notes": ""
  },
  "tkidx_monzen_nakacho_booking_top3_all": {
    "provider": "booking_travelpayouts",
    "area_id": "monzen-nakacho",
    "locale": "all",
    "placement": "top3",
    "destination_ref": "booking_monzen-nakacho",
    "destination_url": "",
    "affiliate_url": "",
    "sub_id": "fs_tkidx_top3_monzen-nakacho_all",
    "enabled": true,
    "priority": 10,
    "last_checked_at": "",
    "notes": ""
  },
  "tkidx_monzen_nakacho_booking_detail_all": {
    "provider": "booking_travelpayouts",
    "area_id": "monzen-nakacho",
    "locale": "all",
    "placement": "detail",
    "destination_ref": "booking_monzen-nakacho",
    "destination_url": "",
    "affiliate_url": "",
    "sub_id": "fs_tkidx_detail_monzen-nakacho_all",
    "enabled": true,
    "priority": 10,
    "last_checked_at": "",
    "notes": ""
  },
  "tkidx_ningyocho_booking_top3_all": {
    "provider": "booking_travelpayouts",
    "area_id": "ningyocho",
    "locale": "all",
    "placement": "top3",
    "destination_ref": "booking_ningyocho",
    "destination_url": "",
    "affiliate_url": "",
    "sub_id": "fs_tkidx_top3_ningyocho_all",
    "enabled": true,
    "priority": 10,
    "last_checked_at": "",
    "notes": ""
  },
  "tkidx_ningyocho_booking_detail_all": {
    "provider": "booking_travelpayouts",
    "area_id": "ningyocho",
    "locale": "all",
    "placement": "detail",
    "destination_ref": "booking_ningyocho",
    "destination_url": "",
    "affiliate_url": "",
    "sub_id": "fs_tkidx_detail_ningyocho_all",
    "enabled": true,
    "priority": 10,
    "last_checked_at": "",
    "notes": ""
  },
  "tkidx_shimbashi_booking_top3_all": {
    "provider": "booking_travelpayouts",
    "area_id": "shimbashi",
    "locale": "all",
    "placement": "top3",
    "destination_ref": "booking_shimbashi",
    "destination_url": "",
    "affiliate_url": "",
    "sub_id": "fs_tkidx_top3_shimbashi_all",
    "enabled": true,
    "priority": 10,
    "last_checked_at": "",
    "notes": ""
  },
  "tkidx_shimbashi_booking_detail_all": {
    "provider": "booking_travelpayouts",
    "area_id": "shimbashi",
    "locale": "all",
    "placement": "detail",
    "destination_ref": "booking_shimbashi",
    "destination_url": "",
    "affiliate_url": "",
    "sub_id": "fs_tkidx_detail_shimbashi_all",
    "enabled": true,
    "priority": 10,
    "last_checked_at": "",
    "notes": ""
  },
  "tkidx_gotanda_booking_top3_all": {
    "provider": "booking_travelpayouts",
    "area_id": "gotanda",
    "locale": "all",
    "placement": "top3",
    "destination_ref": "booking_gotanda",
    "destination_url": "",
    "affiliate_url": "",
    "sub_id": "fs_tkidx_top3_gotanda_all",
    "enabled": true,
    "priority": 10,
    "last_checked_at": "",
    "notes": ""
  },
  "tkidx_gotanda_booking_detail_all": {
    "provider": "booking_travelpayouts",
    "area_id": "gotanda",
    "locale": "all",
    "placement": "detail",
    "destination_ref": "booking_gotanda",
    "destination_url": "",
    "affiliate_url": "",
    "sub_id": "fs_tkidx_detail_gotanda_all",
    "enabled": true,
    "priority": 10,
    "last_checked_at": "",
    "notes": ""
  },
  "tkidx_meguro_booking_top3_all": {
    "provider": "booking_travelpayouts",
    "area_id": "meguro",
    "locale": "all",
    "placement": "top3",
    "destination_ref": "booking_meguro",
    "destination_url": "",
    "affiliate_url": "",
    "sub_id": "fs_tkidx_top3_meguro_all",
    "enabled": true,
    "priority": 10,
    "last_checked_at": "",
    "notes": ""
  },
  "tkidx_meguro_booking_detail_all": {
    "provider": "booking_travelpayouts",
    "area_id": "meguro",
    "locale": "all",
    "placement": "detail",
    "destination_ref": "booking_meguro",
    "destination_url": "",
    "affiliate_url": "",
    "sub_id": "fs_tkidx_detail_meguro_all",
    "enabled": true,
    "priority": 10,
    "last_checked_at": "",
    "notes": ""
  },
  "tkidx_ebisu_booking_top3_all": {
    "provider": "booking_travelpayouts",
    "area_id": "ebisu",
    "locale": "all",
    "placement": "top3",
    "destination_ref": "booking_ebisu",
    "destination_url": "",
    "affiliate_url": "",
    "sub_id": "fs_tkidx_top3_ebisu_all",
    "enabled": true,
    "priority": 10,
    "last_checked_at": "",
    "notes": ""
  },
  "tkidx_ebisu_booking_detail_all": {
    "provider": "booking_travelpayouts",
    "area_id": "ebisu",
    "locale": "all",
    "placement": "detail",
    "destination_ref": "booking_ebisu",
    "destination_url": "",
    "affiliate_url": "",
    "sub_id": "fs_tkidx_detail_ebisu_all",
    "enabled": true,
    "priority": 10,
    "last_checked_at": "",
    "notes": ""
  },
  "tkidx_yoyogi_booking_top3_all": {
    "provider": "booking_travelpayouts",
    "area_id": "yoyogi",
    "locale": "all",
    "placement": "top3",
    "destination_ref": "booking_yoyogi",
    "destination_url": "",
    "affiliate_url": "",
    "sub_id": "fs_tkidx_top3_yoyogi_all",
    "enabled": true,
    "priority": 10,
    "last_checked_at": "",
    "notes": ""
  },
  "tkidx_yoyogi_booking_detail_all": {
    "provider": "booking_travelpayouts",
    "area_id": "yoyogi",
    "locale": "all",
    "placement": "detail",
    "destination_ref": "booking_yoyogi",
    "destination_url": "",
    "affiliate_url": "",
    "sub_id": "fs_tkidx_detail_yoyogi_all",
    "enabled": true,
    "priority": 10,
    "last_checked_at": "",
    "notes": ""
  },
  "tkidx_asakusabashi_booking_top3_all": {
    "provider": "booking_travelpayouts",
    "area_id": "asakusabashi",
    "locale": "all",
    "placement": "top3",
    "destination_ref": "booking_asakusabashi",
    "destination_url": "",
    "affiliate_url": "",
    "sub_id": "fs_tkidx_top3_asakusabashi_all",
    "enabled": true,
    "priority": 10,
    "last_checked_at": "",
    "notes": ""
  },
  "tkidx_asakusabashi_booking_detail_all": {
    "provider": "booking_travelpayouts",
    "area_id": "asakusabashi",
    "locale": "all",
    "placement": "detail",
    "destination_ref": "booking_asakusabashi",
    "destination_url": "",
    "affiliate_url": "",
    "sub_id": "fs_tkidx_detail_asakusabashi_all",
    "enabled": true,
    "priority": 10,
    "last_checked_at": "",
    "notes": ""
  },
  "tkidx_bakurocho_higashinihombashi_booking_top3_all": {
    "provider": "booking_travelpayouts",
    "area_id": "bakurocho-higashinihombashi",
    "locale": "all",
    "placement": "top3",
    "destination_ref": "booking_bakurocho-higashinihombashi",
    "destination_url": "",
    "affiliate_url": "",
    "sub_id": "fs_tkidx_top3_bakurocho-higashinihombashi_all",
    "enabled": true,
    "priority": 10,
    "last_checked_at": "",
    "notes": ""
  },
  "tkidx_bakurocho_higashinihombashi_booking_detail_all": {
    "provider": "booking_travelpayouts",
    "area_id": "bakurocho-higashinihombashi",
    "locale": "all",
    "placement": "detail",
    "destination_ref": "booking_bakurocho-higashinihombashi",
    "destination_url": "",
    "affiliate_url": "",
    "sub_id": "fs_tkidx_detail_bakurocho-higashinihombashi_all",
    "enabled": true,
    "priority": 10,
    "last_checked_at": "",
    "notes": ""
  },
  "tkidx_kinshicho_booking_top3_all": {
    "provider": "booking_travelpayouts",
    "area_id": "kinshicho",
    "locale": "all",
    "placement": "top3",
    "destination_ref": "booking_kinshicho",
    "destination_url": "",
    "affiliate_url": "",
    "sub_id": "fs_tkidx_top3_kinshicho_all",
    "enabled": true,
    "priority": 10,
    "last_checked_at": "",
    "notes": ""
  },
  "tkidx_kinshicho_booking_detail_all": {
    "provider": "booking_travelpayouts",
    "area_id": "kinshicho",
    "locale": "all",
    "placement": "detail",
    "destination_ref": "booking_kinshicho",
    "destination_url": "",
    "affiliate_url": "",
    "sub_id": "fs_tkidx_detail_kinshicho_all",
    "enabled": true,
    "priority": 10,
    "last_checked_at": "",
    "notes": ""
  },
  "tkidx_akasaka_mitsuke_booking_top3_all": {
    "provider": "booking_travelpayouts",
    "area_id": "akasaka-mitsuke",
    "locale": "all",
    "placement": "top3",
    "destination_ref": "booking_akasaka-mitsuke",
    "destination_url": "",
    "affiliate_url": "",
    "sub_id": "fs_tkidx_top3_akasaka-mitsuke_all",
    "enabled": true,
    "priority": 10,
    "last_checked_at": "",
    "notes": ""
  },
  "tkidx_akasaka_mitsuke_booking_detail_all": {
    "provider": "booking_travelpayouts",
    "area_id": "akasaka-mitsuke",
    "locale": "all",
    "placement": "detail",
    "destination_ref": "booking_akasaka-mitsuke",
    "destination_url": "",
    "affiliate_url": "",
    "sub_id": "fs_tkidx_detail_akasaka-mitsuke_all",
    "enabled": true,
    "priority": 10,
    "last_checked_at": "",
    "notes": ""
  },
  "tkidx_roppongi_booking_top3_all": {
    "provider": "booking_travelpayouts",
    "area_id": "roppongi",
    "locale": "all",
    "placement": "top3",
    "destination_ref": "booking_roppongi",
    "destination_url": "",
    "affiliate_url": "",
    "sub_id": "fs_tkidx_top3_roppongi_all",
    "enabled": true,
    "priority": 10,
    "last_checked_at": "",
    "notes": ""
  },
  "tkidx_roppongi_booking_detail_all": {
    "provider": "booking_travelpayouts",
    "area_id": "roppongi",
    "locale": "all",
    "placement": "detail",
    "destination_ref": "booking_roppongi",
    "destination_url": "",
    "affiliate_url": "",
    "sub_id": "fs_tkidx_detail_roppongi_all",
    "enabled": true,
    "priority": 10,
    "last_checked_at": "",
    "notes": ""
  },
  "tkidx_aoyama_omotesando_booking_top3_all": {
    "provider": "booking_travelpayouts",
    "area_id": "aoyama-omotesando",
    "locale": "all",
    "placement": "top3",
    "destination_ref": "booking_aoyama-omotesando",
    "destination_url": "",
    "affiliate_url": "",
    "sub_id": "fs_tkidx_top3_aoyama-omotesando_all",
    "enabled": true,
    "priority": 10,
    "last_checked_at": "",
    "notes": ""
  },
  "tkidx_aoyama_omotesando_booking_detail_all": {
    "provider": "booking_travelpayouts",
    "area_id": "aoyama-omotesando",
    "locale": "all",
    "placement": "detail",
    "destination_ref": "booking_aoyama-omotesando",
    "destination_url": "",
    "affiliate_url": "",
    "sub_id": "fs_tkidx_detail_aoyama-omotesando_all",
    "enabled": true,
    "priority": 10,
    "last_checked_at": "",
    "notes": ""
  },
  "tkidx_ochanomizu_booking_top3_all": {
    "provider": "booking_travelpayouts",
    "area_id": "ochanomizu",
    "locale": "all",
    "placement": "top3",
    "destination_ref": "booking_ochanomizu",
    "destination_url": "",
    "affiliate_url": "",
    "sub_id": "fs_tkidx_top3_ochanomizu_all",
    "enabled": true,
    "priority": 10,
    "last_checked_at": "",
    "notes": ""
  },
  "tkidx_ochanomizu_booking_detail_all": {
    "provider": "booking_travelpayouts",
    "area_id": "ochanomizu",
    "locale": "all",
    "placement": "detail",
    "destination_ref": "booking_ochanomizu",
    "destination_url": "",
    "affiliate_url": "",
    "sub_id": "fs_tkidx_detail_ochanomizu_all",
    "enabled": true,
    "priority": 10,
    "last_checked_at": "",
    "notes": ""
  },
  "tkidx_iidabashi_booking_top3_all": {
    "provider": "booking_travelpayouts",
    "area_id": "iidabashi",
    "locale": "all",
    "placement": "top3",
    "destination_ref": "booking_iidabashi",
    "destination_url": "",
    "affiliate_url": "",
    "sub_id": "fs_tkidx_top3_iidabashi_all",
    "enabled": true,
    "priority": 10,
    "last_checked_at": "",
    "notes": ""
  },
  "tkidx_iidabashi_booking_detail_all": {
    "provider": "booking_travelpayouts",
    "area_id": "iidabashi",
    "locale": "all",
    "placement": "detail",
    "destination_ref": "booking_iidabashi",
    "destination_url": "",
    "affiliate_url": "",
    "sub_id": "fs_tkidx_detail_iidabashi_all",
    "enabled": true,
    "priority": 10,
    "last_checked_at": "",
    "notes": ""
  },
  "tkidx_korakuen_kasuga_booking_top3_all": {
    "provider": "booking_travelpayouts",
    "area_id": "korakuen-kasuga",
    "locale": "all",
    "placement": "top3",
    "destination_ref": "booking_korakuen-kasuga",
    "destination_url": "",
    "affiliate_url": "",
    "sub_id": "fs_tkidx_top3_korakuen-kasuga_all",
    "enabled": true,
    "priority": 10,
    "last_checked_at": "",
    "notes": ""
  },
  "tkidx_korakuen_kasuga_booking_detail_all": {
    "provider": "booking_travelpayouts",
    "area_id": "korakuen-kasuga",
    "locale": "all",
    "placement": "detail",
    "destination_ref": "booking_korakuen-kasuga",
    "destination_url": "",
    "affiliate_url": "",
    "sub_id": "fs_tkidx_detail_korakuen-kasuga_all",
    "enabled": true,
    "priority": 10,
    "last_checked_at": "",
    "notes": ""
  },
  "tkidx_toyosu_booking_top3_all": {
    "provider": "booking_travelpayouts",
    "area_id": "toyosu",
    "locale": "all",
    "placement": "top3",
    "destination_ref": "booking_toyosu",
    "destination_url": "",
    "affiliate_url": "",
    "sub_id": "fs_tkidx_top3_toyosu_all",
    "enabled": true,
    "priority": 10,
    "last_checked_at": "",
    "notes": ""
  },
  "tkidx_toyosu_booking_detail_all": {
    "provider": "booking_travelpayouts",
    "area_id": "toyosu",
    "locale": "all",
    "placement": "detail",
    "destination_ref": "booking_toyosu",
    "destination_url": "",
    "affiliate_url": "",
    "sub_id": "fs_tkidx_detail_toyosu_all",
    "enabled": true,
    "priority": 10,
    "last_checked_at": "",
    "notes": ""
  },
  "tkidx_ariake_odaiba_booking_top3_all": {
    "provider": "booking_travelpayouts",
    "area_id": "ariake-odaiba",
    "locale": "all",
    "placement": "top3",
    "destination_ref": "booking_ariake-odaiba",
    "destination_url": "",
    "affiliate_url": "",
    "sub_id": "fs_tkidx_top3_ariake-odaiba_all",
    "enabled": true,
    "priority": 10,
    "last_checked_at": "",
    "notes": ""
  },
  "tkidx_ariake_odaiba_booking_detail_all": {
    "provider": "booking_travelpayouts",
    "area_id": "ariake-odaiba",
    "locale": "all",
    "placement": "detail",
    "destination_ref": "booking_ariake-odaiba",
    "destination_url": "",
    "affiliate_url": "",
    "sub_id": "fs_tkidx_detail_ariake-odaiba_all",
    "enabled": true,
    "priority": 10,
    "last_checked_at": "",
    "notes": ""
  },
  "tkfirst_shinjuku_booking_card_all": {
    "provider": "booking_travelpayouts",
    "area_id": "shinjuku",
    "locale": "all",
    "placement": "tokyo_first_time_card",
    "destination_url": "",
    "affiliate_url": "",
    "sub_id": "fs_tkfirst_card_shinjuku_all",
    "enabled": true,
    "priority": 10,
    "last_checked_at": "",
    "notes": "",
    "destination_ref": "booking_shinjuku"
  },
  "shinkansen_stay_shinjuku_booking_card_all": {
    "provider": "booking_travelpayouts",
    "area_id": "shinjuku",
    "locale": "all",
    "placement": "before_shinkansen_card",
    "destination_url": "",
    "affiliate_url": "",
    "sub_id": "fs_shinkansen_stay_shinjuku_all",
    "enabled": true,
    "priority": 10,
    "last_checked_at": "",
    "notes": "",
    "destination_ref": "booking_shinjuku"
  },
  "tkfirst_ueno_booking_card_all": {
    "provider": "booking_travelpayouts",
    "area_id": "ueno",
    "locale": "all",
    "placement": "tokyo_first_time_card",
    "destination_url": "",
    "affiliate_url": "",
    "sub_id": "fs_tkfirst_card_ueno_all",
    "enabled": true,
    "priority": 10,
    "last_checked_at": "",
    "notes": "",
    "destination_ref": "booking_ueno"
  },
  "shinkansen_stay_ueno_booking_card_all": {
    "provider": "booking_travelpayouts",
    "area_id": "ueno",
    "locale": "all",
    "placement": "before_shinkansen_card",
    "destination_url": "",
    "affiliate_url": "",
    "sub_id": "fs_shinkansen_stay_ueno_all",
    "enabled": true,
    "priority": 10,
    "last_checked_at": "",
    "notes": "",
    "destination_ref": "booking_ueno"
  },
  "tkfirst_asakusa_booking_card_all": {
    "provider": "booking_travelpayouts",
    "area_id": "asakusa",
    "locale": "all",
    "placement": "tokyo_first_time_card",
    "destination_url": "",
    "affiliate_url": "",
    "sub_id": "fs_tkfirst_card_asakusa_all",
    "enabled": true,
    "priority": 10,
    "last_checked_at": "",
    "notes": "",
    "destination_ref": "booking_asakusa"
  },
  "shinkansen_stay_asakusa_booking_card_all": {
    "provider": "booking_travelpayouts",
    "area_id": "asakusa",
    "locale": "all",
    "placement": "before_shinkansen_card",
    "destination_url": "",
    "affiliate_url": "",
    "sub_id": "fs_shinkansen_stay_asakusa_all",
    "enabled": true,
    "priority": 10,
    "last_checked_at": "",
    "notes": "",
    "destination_ref": "booking_asakusa"
  },
  "tkfirst_tokyo_station_booking_card_all": {
    "provider": "booking_travelpayouts",
    "area_id": "tokyo-station",
    "locale": "all",
    "placement": "tokyo_first_time_card",
    "destination_url": "",
    "affiliate_url": "",
    "sub_id": "fs_tkfirst_card_tokyo-station_all",
    "enabled": true,
    "priority": 10,
    "last_checked_at": "",
    "notes": "",
    "destination_ref": "booking_tokyo-station"
  },
  "shinkansen_stay_tokyo_station_booking_card_all": {
    "provider": "booking_travelpayouts",
    "area_id": "tokyo-station",
    "locale": "all",
    "placement": "before_shinkansen_card",
    "destination_url": "",
    "affiliate_url": "",
    "sub_id": "fs_shinkansen_stay_tokyo-station_all",
    "enabled": true,
    "priority": 10,
    "last_checked_at": "",
    "notes": "",
    "destination_ref": "booking_tokyo-station"
  },
  "tkfirst_ginza_yurakucho_booking_card_all": {
    "provider": "booking_travelpayouts",
    "area_id": "ginza-yurakucho",
    "locale": "all",
    "placement": "tokyo_first_time_card",
    "destination_url": "",
    "affiliate_url": "",
    "sub_id": "fs_tkfirst_card_ginza-yurakucho_all",
    "enabled": true,
    "priority": 10,
    "last_checked_at": "",
    "notes": "",
    "destination_ref": "booking_ginza-yurakucho"
  },
  "shinkansen_stay_ginza_yurakucho_booking_card_all": {
    "provider": "booking_travelpayouts",
    "area_id": "ginza-yurakucho",
    "locale": "all",
    "placement": "before_shinkansen_card",
    "destination_url": "",
    "affiliate_url": "",
    "sub_id": "fs_shinkansen_stay_ginza-yurakucho_all",
    "enabled": true,
    "priority": 10,
    "last_checked_at": "",
    "notes": "",
    "destination_ref": "booking_ginza-yurakucho"
  },
  "compare_tokyo_station_vs_shinjuku_tokyo_station_booking_area_all": {
    "provider": "booking_travelpayouts",
    "area_id": "tokyo-station",
    "locale": "all",
    "placement": "comparison_area_cta",
    "destination_url": "",
    "affiliate_url": "",
    "sub_id": "fs_compare_tokyo-station-vs-shinjuku_tokyo-station_all",
    "enabled": true,
    "priority": 10,
    "last_checked_at": "",
    "notes": "",
    "destination_ref": "booking_tokyo-station",
    "page_group": "tokyo-station-vs-shinjuku"
  },
  "compare_tokyo_station_vs_shinjuku_shinjuku_booking_area_all": {
    "provider": "booking_travelpayouts",
    "area_id": "shinjuku",
    "locale": "all",
    "placement": "comparison_area_cta",
    "destination_url": "",
    "affiliate_url": "",
    "sub_id": "fs_compare_tokyo-station-vs-shinjuku_shinjuku_all",
    "enabled": true,
    "priority": 10,
    "last_checked_at": "",
    "notes": "",
    "destination_ref": "booking_shinjuku",
    "page_group": "tokyo-station-vs-shinjuku"
  },
  "compare_ueno_vs_shinjuku_ueno_booking_area_all": {
    "provider": "booking_travelpayouts",
    "area_id": "ueno",
    "locale": "all",
    "placement": "comparison_area_cta",
    "destination_url": "",
    "affiliate_url": "",
    "sub_id": "fs_compare_ueno-vs-shinjuku_ueno_all",
    "enabled": true,
    "priority": 10,
    "last_checked_at": "",
    "notes": "",
    "destination_ref": "booking_ueno",
    "page_group": "ueno-vs-shinjuku"
  },
  "compare_ueno_vs_shinjuku_shinjuku_booking_area_all": {
    "provider": "booking_travelpayouts",
    "area_id": "shinjuku",
    "locale": "all",
    "placement": "comparison_area_cta",
    "destination_url": "",
    "affiliate_url": "",
    "sub_id": "fs_compare_ueno-vs-shinjuku_shinjuku_all",
    "enabled": true,
    "priority": 10,
    "last_checked_at": "",
    "notes": "",
    "destination_ref": "booking_shinjuku",
    "page_group": "ueno-vs-shinjuku"
  },
  "compare_asakusa_vs_ueno_asakusa_booking_area_all": {
    "provider": "booking_travelpayouts",
    "area_id": "asakusa",
    "locale": "all",
    "placement": "comparison_area_cta",
    "destination_url": "",
    "affiliate_url": "",
    "sub_id": "fs_compare_asakusa-vs-ueno_asakusa_all",
    "enabled": true,
    "priority": 10,
    "last_checked_at": "",
    "notes": "",
    "destination_ref": "booking_asakusa",
    "page_group": "asakusa-vs-ueno"
  },
  "compare_asakusa_vs_ueno_ueno_booking_area_all": {
    "provider": "booking_travelpayouts",
    "area_id": "ueno",
    "locale": "all",
    "placement": "comparison_area_cta",
    "destination_url": "",
    "affiliate_url": "",
    "sub_id": "fs_compare_asakusa-vs-ueno_ueno_all",
    "enabled": true,
    "priority": 10,
    "last_checked_at": "",
    "notes": "",
    "destination_ref": "booking_ueno",
    "page_group": "asakusa-vs-ueno"
  },
  "airport_first_night_ueno_booking_all": {
    "provider": "booking_travelpayouts",
    "area_id": "ueno",
    "locale": "all",
    "placement": "airport_page_first_night_cta",
    "destination_url": "",
    "affiliate_url": "",
    "sub_id": "fs_airport_firstnight_ueno_all",
    "enabled": true,
    "priority": 10,
    "last_checked_at": "",
    "notes": "",
    "destination_ref": "booking_ueno"
  },
  "airport_first_night_asakusa_booking_all": {
    "provider": "booking_travelpayouts",
    "area_id": "asakusa",
    "locale": "all",
    "placement": "airport_page_first_night_cta",
    "destination_url": "",
    "affiliate_url": "",
    "sub_id": "fs_airport_firstnight_asakusa_all",
    "enabled": true,
    "priority": 10,
    "last_checked_at": "",
    "notes": "",
    "destination_ref": "booking_asakusa"
  },
  "airport_first_night_tokyo_station_booking_all": {
    "provider": "booking_travelpayouts",
    "area_id": "tokyo-station",
    "locale": "all",
    "placement": "airport_page_first_night_cta",
    "destination_url": "",
    "affiliate_url": "",
    "sub_id": "fs_airport_firstnight_tokyo-station_all",
    "enabled": true,
    "priority": 10,
    "last_checked_at": "",
    "notes": "",
    "destination_ref": "booking_tokyo-station"
  },
  "airport_first_night_shinjuku_booking_all": {
    "provider": "booking_travelpayouts",
    "area_id": "shinjuku",
    "locale": "all",
    "placement": "airport_page_first_night_cta",
    "destination_url": "",
    "affiliate_url": "",
    "sub_id": "fs_airport_firstnight_shinjuku_all",
    "enabled": true,
    "priority": 10,
    "last_checked_at": "",
    "notes": "",
    "destination_ref": "booking_shinjuku"
  },
  "airport_first_night_shibuya_booking_all": {
    "provider": "booking_travelpayouts",
    "area_id": "shibuya",
    "locale": "all",
    "placement": "airport_page_first_night_cta",
    "destination_url": "",
    "affiliate_url": "",
    "sub_id": "fs_airport_firstnight_shibuya_all",
    "enabled": true,
    "priority": 10,
    "last_checked_at": "",
    "notes": "",
    "destination_ref": "booking_shibuya"
  },
  "airport_first_night_oshiage_booking_all": {
    "provider": "booking_travelpayouts",
    "area_id": "oshiage",
    "locale": "all",
    "placement": "airport_page_first_night_cta",
    "destination_url": "",
    "affiliate_url": "",
    "sub_id": "fs_airport_firstnight_oshiage_all",
    "enabled": true,
    "priority": 10,
    "last_checked_at": "",
    "notes": "",
    "destination_ref": "booking_oshiage"
  },
  "tkhotels_asakusa_booking_hero_all": {
    "provider": "booking_travelpayouts",
    "area_id": "asakusa",
    "locale": "all",
    "placement": "tokyo_hotels_hero",
    "destination_url": "",
    "affiliate_url": "",
    "sub_id": "fs_hotels_asakusa_hero_booking",
    "enabled": true,
    "priority": 10,
    "last_checked_at": "",
    "notes": "",
    "destination_ref": "booking_asakusa"
  },
  "tkhotels_asakusa_booking_bottom_all": {
    "provider": "booking_travelpayouts",
    "area_id": "asakusa",
    "locale": "all",
    "placement": "tokyo_hotels_bottom",
    "destination_url": "",
    "affiliate_url": "",
    "sub_id": "fs_hotels_asakusa_bottom_booking",
    "enabled": true,
    "priority": 10,
    "last_checked_at": "",
    "notes": "",
    "destination_ref": "booking_asakusa"
  },
  "tkhotels_ueno_booking_hero_all": {
    "provider": "booking_travelpayouts",
    "area_id": "ueno",
    "locale": "all",
    "placement": "tokyo_hotels_hero",
    "destination_url": "",
    "affiliate_url": "",
    "sub_id": "fs_hotels_ueno_hero_booking",
    "enabled": true,
    "priority": 10,
    "last_checked_at": "",
    "notes": "",
    "destination_ref": "booking_ueno"
  },
  "tkhotels_ueno_booking_bottom_all": {
    "provider": "booking_travelpayouts",
    "area_id": "ueno",
    "locale": "all",
    "placement": "tokyo_hotels_bottom",
    "destination_url": "",
    "affiliate_url": "",
    "sub_id": "fs_hotels_ueno_bottom_booking",
    "enabled": true,
    "priority": 10,
    "last_checked_at": "",
    "notes": "",
    "destination_ref": "booking_ueno"
  },
  "tkhotels_tokyo-station_booking_hero_all": {
    "provider": "booking_travelpayouts",
    "area_id": "tokyo-station",
    "locale": "all",
    "placement": "tokyo_hotels_hero",
    "destination_url": "",
    "affiliate_url": "",
    "sub_id": "fs_hotels_tokyo_station_hero_booking",
    "enabled": true,
    "priority": 10,
    "last_checked_at": "",
    "notes": "",
    "destination_ref": "booking_tokyo-station"
  },
  "tkhotels_tokyo-station_booking_bottom_all": {
    "provider": "booking_travelpayouts",
    "area_id": "tokyo-station",
    "locale": "all",
    "placement": "tokyo_hotels_bottom",
    "destination_url": "",
    "affiliate_url": "",
    "sub_id": "fs_hotels_tokyo_station_bottom_booking",
    "enabled": true,
    "priority": 10,
    "last_checked_at": "",
    "notes": "",
    "destination_ref": "booking_tokyo-station"
  },
  "tkhotels_ginza-yurakucho_booking_hero_all": {
    "provider": "booking_travelpayouts",
    "area_id": "ginza-yurakucho",
    "locale": "all",
    "placement": "tokyo_hotels_hero",
    "destination_url": "",
    "affiliate_url": "",
    "sub_id": "fs_hotels_ginza_yurakucho_hero_booking",
    "enabled": true,
    "priority": 10,
    "last_checked_at": "",
    "notes": "",
    "destination_ref": "booking_ginza-yurakucho"
  },
  "tkhotels_ginza-yurakucho_booking_bottom_all": {
    "provider": "booking_travelpayouts",
    "area_id": "ginza-yurakucho",
    "locale": "all",
    "placement": "tokyo_hotels_bottom",
    "destination_url": "",
    "affiliate_url": "",
    "sub_id": "fs_hotels_ginza_yurakucho_bottom_booking",
    "enabled": true,
    "priority": 10,
    "last_checked_at": "",
    "notes": "",
    "destination_ref": "booking_ginza-yurakucho"
  },
  "tkhotels_nihombashi_booking_hero_all": {
    "provider": "booking_travelpayouts",
    "area_id": "nihombashi",
    "locale": "all",
    "placement": "tokyo_hotels_hero",
    "destination_url": "",
    "affiliate_url": "",
    "sub_id": "fs_hotels_nihombashi_hero_booking",
    "enabled": true,
    "priority": 10,
    "last_checked_at": "",
    "notes": "",
    "destination_ref": "booking_nihombashi"
  },
  "tkhotels_nihombashi_booking_bottom_all": {
    "provider": "booking_travelpayouts",
    "area_id": "nihombashi",
    "locale": "all",
    "placement": "tokyo_hotels_bottom",
    "destination_url": "",
    "affiliate_url": "",
    "sub_id": "fs_hotels_nihombashi_bottom_booking",
    "enabled": true,
    "priority": 10,
    "last_checked_at": "",
    "notes": "",
    "destination_ref": "booking_nihombashi"
  },
  "tkhotels_shinjuku_booking_hero_all": {
    "provider": "booking_travelpayouts",
    "area_id": "shinjuku",
    "locale": "all",
    "placement": "tokyo_hotels_hero",
    "destination_url": "",
    "affiliate_url": "",
    "sub_id": "fs_hotels_shinjuku_hero_booking",
    "enabled": true,
    "priority": 10,
    "last_checked_at": "",
    "notes": "",
    "destination_ref": "booking_shinjuku"
  },
  "tkhotels_shinjuku_booking_bottom_all": {
    "provider": "booking_travelpayouts",
    "area_id": "shinjuku",
    "locale": "all",
    "placement": "tokyo_hotels_bottom",
    "destination_url": "",
    "affiliate_url": "",
    "sub_id": "fs_hotels_shinjuku_bottom_booking",
    "enabled": true,
    "priority": 10,
    "last_checked_at": "",
    "notes": "",
    "destination_ref": "booking_shinjuku"
  },
  "tkhotels_shibuya_booking_hero_all": {
    "provider": "booking_travelpayouts",
    "area_id": "shibuya",
    "locale": "all",
    "placement": "tokyo_hotels_hero",
    "destination_url": "",
    "affiliate_url": "",
    "sub_id": "fs_hotels_shibuya_hero_booking",
    "enabled": true,
    "priority": 10,
    "last_checked_at": "",
    "notes": "",
    "destination_ref": "booking_shibuya"
  },
  "tkhotels_shibuya_booking_bottom_all": {
    "provider": "booking_travelpayouts",
    "area_id": "shibuya",
    "locale": "all",
    "placement": "tokyo_hotels_bottom",
    "destination_url": "",
    "affiliate_url": "",
    "sub_id": "fs_hotels_shibuya_bottom_booking",
    "enabled": true,
    "priority": 10,
    "last_checked_at": "",
    "notes": "",
    "destination_ref": "booking_shibuya"
  },
  "tkhotels_hamamatsucho-daimon_booking_hero_all": {
    "provider": "booking_travelpayouts",
    "area_id": "hamamatsucho-daimon",
    "locale": "all",
    "placement": "tokyo_hotels_hero",
    "destination_url": "",
    "affiliate_url": "",
    "sub_id": "fs_hotels_hamamatsucho_daimon_hero_booking",
    "enabled": true,
    "priority": 10,
    "last_checked_at": "",
    "notes": "",
    "destination_ref": "booking_hamamatsucho-daimon"
  },
  "tkhotels_hamamatsucho-daimon_booking_bottom_all": {
    "provider": "booking_travelpayouts",
    "area_id": "hamamatsucho-daimon",
    "locale": "all",
    "placement": "tokyo_hotels_bottom",
    "destination_url": "",
    "affiliate_url": "",
    "sub_id": "fs_hotels_hamamatsucho_daimon_bottom_booking",
    "enabled": true,
    "priority": 10,
    "last_checked_at": "",
    "notes": "",
    "destination_ref": "booking_hamamatsucho-daimon"
  },
  "tkhotels_shinagawa_booking_hero_all": {
    "provider": "booking_travelpayouts",
    "area_id": "shinagawa",
    "locale": "all",
    "placement": "tokyo_hotels_hero",
    "destination_url": "",
    "affiliate_url": "",
    "sub_id": "fs_hotels_shinagawa_hero_booking",
    "enabled": true,
    "priority": 10,
    "last_checked_at": "",
    "notes": "",
    "destination_ref": "booking_shinagawa"
  },
  "tkhotels_shinagawa_booking_bottom_all": {
    "provider": "booking_travelpayouts",
    "area_id": "shinagawa",
    "locale": "all",
    "placement": "tokyo_hotels_bottom",
    "destination_url": "",
    "affiliate_url": "",
    "sub_id": "fs_hotels_shinagawa_bottom_booking",
    "enabled": true,
    "priority": 10,
    "last_checked_at": "",
    "notes": "",
    "destination_ref": "booking_shinagawa"
  },
  "tkhotels_kuramae_booking_hero_all": {
    "provider": "booking_travelpayouts",
    "area_id": "kuramae",
    "locale": "all",
    "placement": "tokyo_hotels_hero",
    "destination_url": "",
    "affiliate_url": "",
    "sub_id": "fs_hotels_kuramae_hero_booking",
    "enabled": true,
    "priority": 10,
    "last_checked_at": "",
    "notes": "",
    "destination_ref": "booking_kuramae"
  },
  "tkhotels_kuramae_booking_bottom_all": {
    "provider": "booking_travelpayouts",
    "area_id": "kuramae",
    "locale": "all",
    "placement": "tokyo_hotels_bottom",
    "destination_url": "",
    "affiliate_url": "",
    "sub_id": "fs_hotels_kuramae_bottom_booking",
    "enabled": true,
    "priority": 10,
    "last_checked_at": "",
    "notes": "",
    "destination_ref": "booking_kuramae"
  },
  "tkhotels_oshiage_booking_hero_all": {
    "provider": "booking_travelpayouts",
    "area_id": "oshiage",
    "locale": "all",
    "placement": "tokyo_hotels_hero",
    "destination_url": "",
    "affiliate_url": "",
    "sub_id": "fs_hotels_oshiage_hero_booking",
    "enabled": true,
    "priority": 10,
    "last_checked_at": "",
    "notes": "",
    "destination_ref": "booking_oshiage"
  },
  "tkhotels_oshiage_booking_bottom_all": {
    "provider": "booking_travelpayouts",
    "area_id": "oshiage",
    "locale": "all",
    "placement": "tokyo_hotels_bottom",
    "destination_url": "",
    "affiliate_url": "",
    "sub_id": "fs_hotels_oshiage_bottom_booking",
    "enabled": true,
    "priority": 10,
    "last_checked_at": "",
    "notes": "",
    "destination_ref": "booking_oshiage"
  },
  "tkhotels_ryogoku_booking_hero_all": {
    "provider": "booking_travelpayouts",
    "area_id": "ryogoku",
    "locale": "all",
    "placement": "tokyo_hotels_hero",
    "destination_url": "",
    "affiliate_url": "",
    "sub_id": "fs_hotels_ryogoku_hero_booking",
    "enabled": true,
    "priority": 10,
    "last_checked_at": "",
    "notes": "",
    "destination_ref": "booking_ryogoku"
  },
  "tkhotels_ryogoku_booking_bottom_all": {
    "provider": "booking_travelpayouts",
    "area_id": "ryogoku",
    "locale": "all",
    "placement": "tokyo_hotels_bottom",
    "destination_url": "",
    "affiliate_url": "",
    "sub_id": "fs_hotels_ryogoku_bottom_booking",
    "enabled": true,
    "priority": 10,
    "last_checked_at": "",
    "notes": "",
    "destination_ref": "booking_ryogoku"
  },
  "tkhotels_kiyosumi-shirakawa_booking_hero_all": {
    "provider": "booking_travelpayouts",
    "area_id": "kiyosumi-shirakawa",
    "locale": "all",
    "placement": "tokyo_hotels_hero",
    "destination_url": "",
    "affiliate_url": "",
    "sub_id": "fs_hotels_kiyosumi_shirakawa_hero_booking",
    "enabled": true,
    "priority": 10,
    "last_checked_at": "",
    "notes": "",
    "destination_ref": "booking_kiyosumi-shirakawa"
  },
  "tkhotels_kiyosumi-shirakawa_booking_bottom_all": {
    "provider": "booking_travelpayouts",
    "area_id": "kiyosumi-shirakawa",
    "locale": "all",
    "placement": "tokyo_hotels_bottom",
    "destination_url": "",
    "affiliate_url": "",
    "sub_id": "fs_hotels_kiyosumi_shirakawa_bottom_booking",
    "enabled": true,
    "priority": 10,
    "last_checked_at": "",
    "notes": "",
    "destination_ref": "booking_kiyosumi-shirakawa"
  },
  "tkhotels_monzen-nakacho_booking_hero_all": {
    "provider": "booking_travelpayouts",
    "area_id": "monzen-nakacho",
    "locale": "all",
    "placement": "tokyo_hotels_hero",
    "destination_url": "",
    "affiliate_url": "",
    "sub_id": "fs_hotels_monzen_nakacho_hero_booking",
    "enabled": true,
    "priority": 10,
    "last_checked_at": "",
    "notes": "",
    "destination_ref": "booking_monzen-nakacho"
  },
  "tkhotels_monzen-nakacho_booking_bottom_all": {
    "provider": "booking_travelpayouts",
    "area_id": "monzen-nakacho",
    "locale": "all",
    "placement": "tokyo_hotels_bottom",
    "destination_url": "",
    "affiliate_url": "",
    "sub_id": "fs_hotels_monzen_nakacho_bottom_booking",
    "enabled": true,
    "priority": 10,
    "last_checked_at": "",
    "notes": "",
    "destination_ref": "booking_monzen-nakacho"
  },
  "tkhotels_ningyocho_booking_hero_all": {
    "provider": "booking_travelpayouts",
    "area_id": "ningyocho",
    "locale": "all",
    "placement": "tokyo_hotels_hero",
    "destination_url": "",
    "affiliate_url": "",
    "sub_id": "fs_hotels_ningyocho_hero_booking",
    "enabled": true,
    "priority": 10,
    "last_checked_at": "",
    "notes": "",
    "destination_ref": "booking_ningyocho"
  },
  "tkhotels_ningyocho_booking_bottom_all": {
    "provider": "booking_travelpayouts",
    "area_id": "ningyocho",
    "locale": "all",
    "placement": "tokyo_hotels_bottom",
    "destination_url": "",
    "affiliate_url": "",
    "sub_id": "fs_hotels_ningyocho_bottom_booking",
    "enabled": true,
    "priority": 10,
    "last_checked_at": "",
    "notes": "",
    "destination_ref": "booking_ningyocho"
  },
  "tkhotels_hatchobori_booking_hero_all": {
    "provider": "booking_travelpayouts",
    "area_id": "hatchobori",
    "locale": "all",
    "placement": "tokyo_hotels_hero",
    "destination_url": "",
    "affiliate_url": "",
    "sub_id": "fs_hotels_hatchobori_hero_booking",
    "enabled": true,
    "priority": 10,
    "last_checked_at": "",
    "notes": "",
    "destination_ref": "booking_hatchobori"
  },
  "tkhotels_hatchobori_booking_bottom_all": {
    "provider": "booking_travelpayouts",
    "area_id": "hatchobori",
    "locale": "all",
    "placement": "tokyo_hotels_bottom",
    "destination_url": "",
    "affiliate_url": "",
    "sub_id": "fs_hotels_hatchobori_bottom_booking",
    "enabled": true,
    "priority": 10,
    "last_checked_at": "",
    "notes": "",
    "destination_ref": "booking_hatchobori"
  },
  "tkhotels_kayabacho_booking_hero_all": {
    "provider": "booking_travelpayouts",
    "area_id": "kayabacho",
    "locale": "all",
    "placement": "tokyo_hotels_hero",
    "destination_url": "",
    "affiliate_url": "",
    "sub_id": "fs_hotels_kayabacho_hero_booking",
    "enabled": true,
    "priority": 10,
    "last_checked_at": "",
    "notes": "",
    "destination_ref": "booking_kayabacho"
  },
  "tkhotels_kayabacho_booking_bottom_all": {
    "provider": "booking_travelpayouts",
    "area_id": "kayabacho",
    "locale": "all",
    "placement": "tokyo_hotels_bottom",
    "destination_url": "",
    "affiliate_url": "",
    "sub_id": "fs_hotels_kayabacho_bottom_booking",
    "enabled": true,
    "priority": 10,
    "last_checked_at": "",
    "notes": "",
    "destination_ref": "booking_kayabacho"
  },
  "tkhotels_shimbashi_booking_hero_all": {
    "provider": "booking_travelpayouts",
    "area_id": "shimbashi",
    "locale": "all",
    "placement": "tokyo_hotels_hero",
    "destination_url": "",
    "affiliate_url": "",
    "sub_id": "fs_hotels_shimbashi_hero_booking",
    "enabled": true,
    "priority": 10,
    "last_checked_at": "",
    "notes": "",
    "destination_ref": "booking_shimbashi"
  },
  "tkhotels_shimbashi_booking_bottom_all": {
    "provider": "booking_travelpayouts",
    "area_id": "shimbashi",
    "locale": "all",
    "placement": "tokyo_hotels_bottom",
    "destination_url": "",
    "affiliate_url": "",
    "sub_id": "fs_hotels_shimbashi_bottom_booking",
    "enabled": true,
    "priority": 10,
    "last_checked_at": "",
    "notes": "",
    "destination_ref": "booking_shimbashi"
  },
  "tkhotels_gotanda_booking_hero_all": {
    "provider": "booking_travelpayouts",
    "area_id": "gotanda",
    "locale": "all",
    "placement": "tokyo_hotels_hero",
    "destination_url": "",
    "affiliate_url": "",
    "sub_id": "fs_hotels_gotanda_hero_booking",
    "enabled": true,
    "priority": 10,
    "last_checked_at": "",
    "notes": "",
    "destination_ref": "booking_gotanda"
  },
  "tkhotels_gotanda_booking_bottom_all": {
    "provider": "booking_travelpayouts",
    "area_id": "gotanda",
    "locale": "all",
    "placement": "tokyo_hotels_bottom",
    "destination_url": "",
    "affiliate_url": "",
    "sub_id": "fs_hotels_gotanda_bottom_booking",
    "enabled": true,
    "priority": 10,
    "last_checked_at": "",
    "notes": "",
    "destination_ref": "booking_gotanda"
  },
  "tkhotels_meguro_booking_hero_all": {
    "provider": "booking_travelpayouts",
    "area_id": "meguro",
    "locale": "all",
    "placement": "tokyo_hotels_hero",
    "destination_url": "",
    "affiliate_url": "",
    "sub_id": "fs_hotels_meguro_hero_booking",
    "enabled": true,
    "priority": 10,
    "last_checked_at": "",
    "notes": "",
    "destination_ref": "booking_meguro"
  },
  "tkhotels_meguro_booking_bottom_all": {
    "provider": "booking_travelpayouts",
    "area_id": "meguro",
    "locale": "all",
    "placement": "tokyo_hotels_bottom",
    "destination_url": "",
    "affiliate_url": "",
    "sub_id": "fs_hotels_meguro_bottom_booking",
    "enabled": true,
    "priority": 10,
    "last_checked_at": "",
    "notes": "",
    "destination_ref": "booking_meguro"
  },
  "tkhotels_ebisu_booking_hero_all": {
    "provider": "booking_travelpayouts",
    "area_id": "ebisu",
    "locale": "all",
    "placement": "tokyo_hotels_hero",
    "destination_url": "",
    "affiliate_url": "",
    "sub_id": "fs_hotels_ebisu_hero_booking",
    "enabled": true,
    "priority": 10,
    "last_checked_at": "",
    "notes": "",
    "destination_ref": "booking_ebisu"
  },
  "tkhotels_ebisu_booking_bottom_all": {
    "provider": "booking_travelpayouts",
    "area_id": "ebisu",
    "locale": "all",
    "placement": "tokyo_hotels_bottom",
    "destination_url": "",
    "affiliate_url": "",
    "sub_id": "fs_hotels_ebisu_bottom_booking",
    "enabled": true,
    "priority": 10,
    "last_checked_at": "",
    "notes": "",
    "destination_ref": "booking_ebisu"
  },
  "tkhotels_yoyogi_booking_hero_all": {
    "provider": "booking_travelpayouts",
    "area_id": "yoyogi",
    "locale": "all",
    "placement": "tokyo_hotels_hero",
    "destination_url": "",
    "affiliate_url": "",
    "sub_id": "fs_hotels_yoyogi_hero_booking",
    "enabled": true,
    "priority": 10,
    "last_checked_at": "",
    "notes": "",
    "destination_ref": "booking_yoyogi"
  },
  "tkhotels_yoyogi_booking_bottom_all": {
    "provider": "booking_travelpayouts",
    "area_id": "yoyogi",
    "locale": "all",
    "placement": "tokyo_hotels_bottom",
    "destination_url": "",
    "affiliate_url": "",
    "sub_id": "fs_hotels_yoyogi_bottom_booking",
    "enabled": true,
    "priority": 10,
    "last_checked_at": "",
    "notes": "",
    "destination_ref": "booking_yoyogi"
  },
  "tkhotels_ikebukuro_booking_hero_all": {
    "provider": "booking_travelpayouts",
    "area_id": "ikebukuro",
    "locale": "all",
    "placement": "tokyo_hotels_hero",
    "destination_url": "",
    "affiliate_url": "",
    "sub_id": "fs_hotels_ikebukuro_hero_booking",
    "enabled": true,
    "priority": 10,
    "last_checked_at": "",
    "notes": "",
    "destination_ref": "booking_ikebukuro"
  },
  "tkhotels_ikebukuro_booking_bottom_all": {
    "provider": "booking_travelpayouts",
    "area_id": "ikebukuro",
    "locale": "all",
    "placement": "tokyo_hotels_bottom",
    "destination_url": "",
    "affiliate_url": "",
    "sub_id": "fs_hotels_ikebukuro_bottom_booking",
    "enabled": true,
    "priority": 10,
    "last_checked_at": "",
    "notes": "",
    "destination_ref": "booking_ikebukuro"
  },
  "tkhotels_akihabara_booking_hero_all": {
    "provider": "booking_travelpayouts",
    "area_id": "akihabara",
    "locale": "all",
    "placement": "tokyo_hotels_hero",
    "destination_url": "",
    "affiliate_url": "",
    "sub_id": "fs_hotels_akihabara_hero_booking",
    "enabled": true,
    "priority": 10,
    "last_checked_at": "",
    "notes": "",
    "destination_ref": "booking_akihabara"
  },
  "tkhotels_akihabara_booking_bottom_all": {
    "provider": "booking_travelpayouts",
    "area_id": "akihabara",
    "locale": "all",
    "placement": "tokyo_hotels_bottom",
    "destination_url": "",
    "affiliate_url": "",
    "sub_id": "fs_hotels_akihabara_bottom_booking",
    "enabled": true,
    "priority": 10,
    "last_checked_at": "",
    "notes": "",
    "destination_ref": "booking_akihabara"
  },
  "tkhotels_kanda_booking_hero_all": {
    "provider": "booking_travelpayouts",
    "area_id": "kanda",
    "locale": "all",
    "placement": "tokyo_hotels_hero",
    "destination_url": "",
    "affiliate_url": "",
    "sub_id": "fs_hotels_kanda_hero_booking",
    "enabled": true,
    "priority": 10,
    "last_checked_at": "",
    "notes": "",
    "destination_ref": "booking_kanda"
  },
  "tkhotels_kanda_booking_bottom_all": {
    "provider": "booking_travelpayouts",
    "area_id": "kanda",
    "locale": "all",
    "placement": "tokyo_hotels_bottom",
    "destination_url": "",
    "affiliate_url": "",
    "sub_id": "fs_hotels_kanda_bottom_booking",
    "enabled": true,
    "priority": 10,
    "last_checked_at": "",
    "notes": "",
    "destination_ref": "booking_kanda"
  },
  "tkhotels_asakusabashi_booking_hero_all": {
    "provider": "booking_travelpayouts",
    "area_id": "asakusabashi",
    "locale": "all",
    "placement": "tokyo_hotels_hero",
    "destination_url": "",
    "affiliate_url": "",
    "sub_id": "fs_hotels_asakusabashi_hero_booking",
    "enabled": true,
    "priority": 10,
    "last_checked_at": "",
    "notes": "",
    "destination_ref": "booking_asakusabashi"
  },
  "tkhotels_asakusabashi_booking_bottom_all": {
    "provider": "booking_travelpayouts",
    "area_id": "asakusabashi",
    "locale": "all",
    "placement": "tokyo_hotels_bottom",
    "destination_url": "",
    "affiliate_url": "",
    "sub_id": "fs_hotels_asakusabashi_bottom_booking",
    "enabled": true,
    "priority": 10,
    "last_checked_at": "",
    "notes": "",
    "destination_ref": "booking_asakusabashi"
  },
  "tkhotels_bakurocho-higashinihombashi_booking_hero_all": {
    "provider": "booking_travelpayouts",
    "area_id": "bakurocho-higashinihombashi",
    "locale": "all",
    "placement": "tokyo_hotels_hero",
    "destination_url": "",
    "affiliate_url": "",
    "sub_id": "fs_hotels_bakurocho_higashinihombashi_hero_booking",
    "enabled": true,
    "priority": 10,
    "last_checked_at": "",
    "notes": "",
    "destination_ref": "booking_bakurocho-higashinihombashi"
  },
  "tkhotels_bakurocho-higashinihombashi_booking_bottom_all": {
    "provider": "booking_travelpayouts",
    "area_id": "bakurocho-higashinihombashi",
    "locale": "all",
    "placement": "tokyo_hotels_bottom",
    "destination_url": "",
    "affiliate_url": "",
    "sub_id": "fs_hotels_bakurocho_higashinihombashi_bottom_booking",
    "enabled": true,
    "priority": 10,
    "last_checked_at": "",
    "notes": "",
    "destination_ref": "booking_bakurocho-higashinihombashi"
  },
  "tkhotels_kinshicho_booking_hero_all": {
    "provider": "booking_travelpayouts",
    "area_id": "kinshicho",
    "locale": "all",
    "placement": "tokyo_hotels_hero",
    "destination_url": "",
    "affiliate_url": "",
    "sub_id": "fs_hotels_kinshicho_hero_booking",
    "enabled": true,
    "priority": 10,
    "last_checked_at": "",
    "notes": "",
    "destination_ref": "booking_kinshicho"
  },
  "tkhotels_kinshicho_booking_bottom_all": {
    "provider": "booking_travelpayouts",
    "area_id": "kinshicho",
    "locale": "all",
    "placement": "tokyo_hotels_bottom",
    "destination_url": "",
    "affiliate_url": "",
    "sub_id": "fs_hotels_kinshicho_bottom_booking",
    "enabled": true,
    "priority": 10,
    "last_checked_at": "",
    "notes": "",
    "destination_ref": "booking_kinshicho"
  },
  "tkhotels_akasaka-mitsuke_booking_hero_all": {
    "provider": "booking_travelpayouts",
    "area_id": "akasaka-mitsuke",
    "locale": "all",
    "placement": "tokyo_hotels_hero",
    "destination_url": "",
    "affiliate_url": "",
    "sub_id": "fs_hotels_akasaka_mitsuke_hero_booking",
    "enabled": true,
    "priority": 10,
    "last_checked_at": "",
    "notes": "",
    "destination_ref": "booking_akasaka-mitsuke"
  },
  "tkhotels_akasaka-mitsuke_booking_bottom_all": {
    "provider": "booking_travelpayouts",
    "area_id": "akasaka-mitsuke",
    "locale": "all",
    "placement": "tokyo_hotels_bottom",
    "destination_url": "",
    "affiliate_url": "",
    "sub_id": "fs_hotels_akasaka_mitsuke_bottom_booking",
    "enabled": true,
    "priority": 10,
    "last_checked_at": "",
    "notes": "",
    "destination_ref": "booking_akasaka-mitsuke"
  },
  "tkhotels_roppongi_booking_hero_all": {
    "provider": "booking_travelpayouts",
    "area_id": "roppongi",
    "locale": "all",
    "placement": "tokyo_hotels_hero",
    "destination_url": "",
    "affiliate_url": "",
    "sub_id": "fs_hotels_roppongi_hero_booking",
    "enabled": true,
    "priority": 10,
    "last_checked_at": "",
    "notes": "",
    "destination_ref": "booking_roppongi"
  },
  "tkhotels_roppongi_booking_bottom_all": {
    "provider": "booking_travelpayouts",
    "area_id": "roppongi",
    "locale": "all",
    "placement": "tokyo_hotels_bottom",
    "destination_url": "",
    "affiliate_url": "",
    "sub_id": "fs_hotels_roppongi_bottom_booking",
    "enabled": true,
    "priority": 10,
    "last_checked_at": "",
    "notes": "",
    "destination_ref": "booking_roppongi"
  },
  "tkhotels_aoyama-omotesando_booking_hero_all": {
    "provider": "booking_travelpayouts",
    "area_id": "aoyama-omotesando",
    "locale": "all",
    "placement": "tokyo_hotels_hero",
    "destination_url": "",
    "affiliate_url": "",
    "sub_id": "fs_hotels_aoyama_omotesando_hero_booking",
    "enabled": true,
    "priority": 10,
    "last_checked_at": "",
    "notes": "",
    "destination_ref": "booking_aoyama-omotesando"
  },
  "tkhotels_aoyama-omotesando_booking_bottom_all": {
    "provider": "booking_travelpayouts",
    "area_id": "aoyama-omotesando",
    "locale": "all",
    "placement": "tokyo_hotels_bottom",
    "destination_url": "",
    "affiliate_url": "",
    "sub_id": "fs_hotels_aoyama_omotesando_bottom_booking",
    "enabled": true,
    "priority": 10,
    "last_checked_at": "",
    "notes": "",
    "destination_ref": "booking_aoyama-omotesando"
  },
  "tkhotels_ochanomizu_booking_hero_all": {
    "provider": "booking_travelpayouts",
    "area_id": "ochanomizu",
    "locale": "all",
    "placement": "tokyo_hotels_hero",
    "destination_url": "",
    "affiliate_url": "",
    "sub_id": "fs_hotels_ochanomizu_hero_booking",
    "enabled": true,
    "priority": 10,
    "last_checked_at": "",
    "notes": "",
    "destination_ref": "booking_ochanomizu"
  },
  "tkhotels_ochanomizu_booking_bottom_all": {
    "provider": "booking_travelpayouts",
    "area_id": "ochanomizu",
    "locale": "all",
    "placement": "tokyo_hotels_bottom",
    "destination_url": "",
    "affiliate_url": "",
    "sub_id": "fs_hotels_ochanomizu_bottom_booking",
    "enabled": true,
    "priority": 10,
    "last_checked_at": "",
    "notes": "",
    "destination_ref": "booking_ochanomizu"
  },
  "tkhotels_iidabashi_booking_hero_all": {
    "provider": "booking_travelpayouts",
    "area_id": "iidabashi",
    "locale": "all",
    "placement": "tokyo_hotels_hero",
    "destination_url": "",
    "affiliate_url": "",
    "sub_id": "fs_hotels_iidabashi_hero_booking",
    "enabled": true,
    "priority": 10,
    "last_checked_at": "",
    "notes": "",
    "destination_ref": "booking_iidabashi"
  },
  "tkhotels_iidabashi_booking_bottom_all": {
    "provider": "booking_travelpayouts",
    "area_id": "iidabashi",
    "locale": "all",
    "placement": "tokyo_hotels_bottom",
    "destination_url": "",
    "affiliate_url": "",
    "sub_id": "fs_hotels_iidabashi_bottom_booking",
    "enabled": true,
    "priority": 10,
    "last_checked_at": "",
    "notes": "",
    "destination_ref": "booking_iidabashi"
  },
  "tkhotels_korakuen-kasuga_booking_hero_all": {
    "provider": "booking_travelpayouts",
    "area_id": "korakuen-kasuga",
    "locale": "all",
    "placement": "tokyo_hotels_hero",
    "destination_url": "",
    "affiliate_url": "",
    "sub_id": "fs_hotels_korakuen_kasuga_hero_booking",
    "enabled": true,
    "priority": 10,
    "last_checked_at": "",
    "notes": "",
    "destination_ref": "booking_korakuen-kasuga"
  },
  "tkhotels_korakuen-kasuga_booking_bottom_all": {
    "provider": "booking_travelpayouts",
    "area_id": "korakuen-kasuga",
    "locale": "all",
    "placement": "tokyo_hotels_bottom",
    "destination_url": "",
    "affiliate_url": "",
    "sub_id": "fs_hotels_korakuen_kasuga_bottom_booking",
    "enabled": true,
    "priority": 10,
    "last_checked_at": "",
    "notes": "",
    "destination_ref": "booking_korakuen-kasuga"
  },
  "tkhotels_toyosu_booking_hero_all": {
    "provider": "booking_travelpayouts",
    "area_id": "toyosu",
    "locale": "all",
    "placement": "tokyo_hotels_hero",
    "destination_url": "",
    "affiliate_url": "",
    "sub_id": "fs_hotels_toyosu_hero_booking",
    "enabled": true,
    "priority": 10,
    "last_checked_at": "",
    "notes": "",
    "destination_ref": "booking_toyosu"
  },
  "tkhotels_toyosu_booking_bottom_all": {
    "provider": "booking_travelpayouts",
    "area_id": "toyosu",
    "locale": "all",
    "placement": "tokyo_hotels_bottom",
    "destination_url": "",
    "affiliate_url": "",
    "sub_id": "fs_hotels_toyosu_bottom_booking",
    "enabled": true,
    "priority": 10,
    "last_checked_at": "",
    "notes": "",
    "destination_ref": "booking_toyosu"
  },
  "tkhotels_ariake-odaiba_booking_hero_all": {
    "provider": "booking_travelpayouts",
    "area_id": "ariake-odaiba",
    "locale": "all",
    "placement": "tokyo_hotels_hero",
    "destination_url": "",
    "affiliate_url": "",
    "sub_id": "fs_hotels_ariake_odaiba_hero_booking",
    "enabled": true,
    "priority": 10,
    "last_checked_at": "",
    "notes": "",
    "destination_ref": "booking_ariake-odaiba"
  },
  "tkhotels_ariake-odaiba_booking_bottom_all": {
    "provider": "booking_travelpayouts",
    "area_id": "ariake-odaiba",
    "locale": "all",
    "placement": "tokyo_hotels_bottom",
    "destination_url": "",
    "affiliate_url": "",
    "sub_id": "fs_hotels_ariake_odaiba_bottom_booking",
    "enabled": true,
    "priority": 10,
    "last_checked_at": "",
    "notes": "",
    "destination_ref": "booking_ariake-odaiba"
  }
}
